{"reviews":[{"stars":3,"username":"Sp00py","content":"Seems to work fine. Has random resprings that Cr4shed says is caused by gif2aniv2.","version":"2.1","ios":"13.3","date":"2020-01-29T22:30:29.000Z"},{"stars":3,"username":"Maticzpl","content":"Doesnt changw the animation","version":"2.1.1","ios":"12.4","date":"2020-08-13T10:09:54.000Z"},{"stars":5,"username":"xDaemonz","content":"Works fine on 12.4","version":"2.1.1","ios":"12.4","date":"2019-09-15T00:47:30.000Z"},{"stars":3,"username":"Eoik","content":"6s. 13.3. setting gif as respring logo works for me not sure about anything else tho","version":"2.1","ios":"13.3","date":"2020-03-14T22:03:51.000Z"},{"stars":3,"username":"Tamino","content":"It brakes my safemode","version":"2.1","ios":"13.3.1","date":"2020-02-24T06:35:19.000Z"},{"stars":5,"username":"Jo","content":"Works on A12 on iOS 12.1","version":"2.1.1","ios":"12.1","date":"2019-05-12T04:05:29.000Z"},{"stars":4,"username":"The_Blue_Goose","content":"There is a bug when this is on that moves the WiFi, battery, and cellular icons to the left of the notch, leaving the right side empty.","version":"2.1.1","ios":"13.5","date":"2020-06-11T15:47:48.000Z"},{"stars":1,"username":null,"content":"Doesn’t work on Chimera.","version":"2.1","ios":"12.1.1","date":"2019-05-14T13:16:21.000Z"},{"stars":5,"username":null,"content":"Device: iPhone 7+\niOS: 12.1.2\n\n*Install Package From midnightchips repo","version":"2.1.1","ios":"12.1.2","date":"2019-05-31T08:36:42.000Z"},{"stars":3,"username":null,"content":"I cant get in to safe mode\n","version":"2.1","ios":"13.3","date":"2020-03-26T20:14:52.000Z"},{"stars":3,"username":null,"content":"Works but keeps causing a backboardd crash log to appear. ","version":"2.1.1","ios":"13.3","date":"2020-02-06T07:52:51.000Z"},{"stars":5,"username":null,"content":"Iphone X ios 13.3.1","version":"2.1.1","ios":"13.3.1","date":"2020-04-18T11:46:21.000Z"},{"stars":3,"username":null,"content":"Crashes upon selecting any gif on iPad Pro 12.4","version":"2.1.1","ios":"12.4","date":"2019-09-15T23:35:49.000Z"},{"stars":3,"username":null,"content":"Crashing backboardd. ","version":"2.1","ios":"13.5","date":"2020-05-26T03:39:40.000Z"},{"stars":5,"username":null,"content":"Works basically all the time for me, I don’t have complaints. ","version":"2.1.1","ios":"13.2.3","date":"2020-02-02T18:00:01.000Z"},{"stars":3,"username":null,"content":"Works when using ldrestart, but not normal respringing","version":"2.1","ios":"13.3","date":"2020-02-29T13:20:03.000Z"},{"stars":3,"username":null,"content":"Not working iP11 13.5 unc0ver","version":"2.1","ios":"13.5","date":"2020-06-18T06:31:17.000Z"},{"stars":5,"username":null,"content":"Works great \n(Reviewed my @iTollMouS)","version":"2.1.1","ios":"12.1.1","date":"2019-05-20T10:11:47.000Z"},{"stars":3,"username":null,"content":"Preference panel fails to load on iOS 13.5","version":"2.1","ios":"13.5","date":"2020-06-03T20:00:44.000Z"},{"stars":5,"username":null,"content":"Working on iPhone XS Max 12.1","version":"2.1.1","ios":"12.1","date":"2019-05-13T01:11:59.000Z"}],"stars":{"1":3,"2":0,"3":19,"4":1,"5":16},"averageStars":3.69}