{"reviews":[{"stars":3,"username":"LetsBeCivilNow","content":"Respiring on 14.2 (7+  9,2)","version":"2.0.0","ios":"14.2","date":"2020-11-13T18:07:15.000Z"},{"stars":3,"username":"RedRain77","content":"Works 80% of the time but often resprings phone when trying to view notifications.","version":"2.0.0","ios":"13.3","date":"2020-11-17T02:15:53.000Z"},{"stars":5,"username":"Samir4021","content":"iPhone 11 Pro 13.5 working perfectly","version":"2.0.0","ios":"13.5","date":"2020-07-25T01:24:45.000Z"}],"stars":{"1":0,"2":0,"3":4,"4":0,"5":4},"averageStars":4}